playfully/__init__.py
playfully-1.1.1.dist-info/WHEEL
playfully-1.1.1.dist-info/METADATA
playfully-1.1.1.dist-info/RECORD
