Metadata-Version: 2.1
Name: playfully
Version: 1.1.1
Summary: A library for playing with strings.
Author-email: encerio_melojuras123 <mangelsp1965@gmail.com>
Requires-Python: >=3.8
Classifier: Programming Language :: Python :: 3
Classifier: License :: OSI Approved :: The Unlicense (Unlicense)
Classifier: Operating System :: OS Independent
